{
  "lastCrawl": "2026-04-21T23:29:48.307514",
  "sources": {
    "contestkorea": {
      "lastSuccess": "2026-04-21T23:29:49.964565",
      "count": 13,
      "errors": []
    },
    "thinkcontest": {
      "lastSuccess": "2026-04-21T23:29:52.966292",
      "count": 1,
      "errors": []
    },
    "linkareer": {
      "lastSuccess": "2026-04-21T23:30:01.126115",
      "count": 5,
      "errors": []
    },
    "wevity": {
      "lastSuccess": "2026-04-21T23:30:41.865126",
      "count": 15,
      "errors": []
    },
    "dacon": {
      "lastSuccess": "2026-04-21T23:30:43.400144",
      "count": 15,
      "errors": []
    }
  }
}